pixilate/__init__.py
pixilate/__main__.py
pixilate/pixilate_main.py
pixilate-1.0.3.dist-info/LICENSE
pixilate-1.0.3.dist-info/METADATA
pixilate-1.0.3.dist-info/WHEEL
pixilate-1.0.3.dist-info/entry_points.txt
pixilate-1.0.3.dist-info/top_level.txt
pixilate-1.0.3.dist-info/RECORD
