Metadata-Version: 2.1
Name: pixilate
Version: 1.0.3
Summary: converts any image to true color format
Home-page: https://github.com/c00kie17/pixilate
Author: c00kie17
Author-email: anshul1708@gmail.com
License: UNKNOWN
Platform: UNKNOWN
Classifier: Programming Language :: Python :: 3
Classifier: License :: OSI Approved :: MIT License
Classifier: Operating System :: OS Independent
Requires-Dist: pillow
